<?xml version="1.0" encoding="UTF-8"?>
<MetaDataObject xmlns="http://v8.1c.ru/8.3/MDClasses" xmlns:app="http://v8.1c.ru/8.2/managed-application/core" xmlns:cfg="http://v8.1c.ru/8.1/data/enterprise/current-config" xmlns:cmi="http://v8.1c.ru/8.2/managed-application/cmi" xmlns:ent="http://v8.1c.ru/8.1/data/enterprise" xmlns:lf="http://v8.1c.ru/8.2/managed-application/logform" xmlns:style="http://v8.1c.ru/8.1/data/ui/style" xmlns:sys="http://v8.1c.ru/8.1/data/ui/fonts/system" xmlns:v8="http://v8.1c.ru/8.1/data/core" xmlns:v8ui="http://v8.1c.ru/8.1/data/ui" xmlns:web="http://v8.1c.ru/8.1/data/ui/colors/web" xmlns:win="http://v8.1c.ru/8.1/data/ui/colors/windows" xmlns:xen="http://v8.1c.ru/8.3/xcf/enums" xmlns:xpr="http://v8.1c.ru/8.3/xcf/predef" xmlns:xr="http://v8.1c.ru/8.3/xcf/readable" xmlns:xs="http://www.w3.org/2001/XMLSchema" xmlns:xsi="http://www.w3.org/2001/XMLSchema-instance" version="2.4">
	<WebService uuid="d7ce6037-7928-4c7f-bcd1-49f424a6eeb6">
		<Properties>
			<Name>api2</Name>
			<Synonym>
				<v8:item>
					<v8:lang>ru</v8:lang>
					<v8:content>Api2</v8:content>
				</v8:item>
			</Synonym>
			<Comment/>
			<Namespace>www.ai-zoom.ru/xmlshema/api2</Namespace>
			<XDTOPackages/>
			<DescriptorFileName>api2.1cws</DescriptorFileName>
			<ReuseSessions>DontUse</ReuseSessions>
			<SessionMaxAge>20</SessionMaxAge>
		</Properties>
		<ChildObjects>
			<Operation uuid="c3c99190-8e74-4303-bb20-3affc4abf756">
				<Properties>
					<Name>create_check_available</Name>
					<Synonym>
						<v8:item>
							<v8:lang>ru</v8:lang>
							<v8:content>Create check available</v8:content>
						</v8:item>
					</Synonym>
					<Comment/>
					<XDTOReturningValueType>xs:string</XDTOReturningValueType>
					<Nillable>true</Nillable>
					<Transactioned>false</Transactioned>
					<ProcedureName>create_check_available</ProcedureName>
					<DataLockControlMode>Managed</DataLockControlMode>
				</Properties>
				<ChildObjects>
					<Parameter uuid="8f3c3bf9-73d2-432c-b01f-bdb0d9ce16fd">
						<Properties>
							<Name>check_available</Name>
							<Synonym>
								<v8:item>
									<v8:lang>ru</v8:lang>
									<v8:content>Check available</v8:content>
								</v8:item>
							</Synonym>
							<Comment/>
							<XDTOValueType>xs:string</XDTOValueType>
							<Nillable>false</Nillable>
							<TransferDirection>In</TransferDirection>
						</Properties>
					</Parameter>
					<Parameter uuid="b6b4fcf1-79a5-4d98-9255-b5740a0f212b">
						<Properties>
							<Name>err</Name>
							<Synonym>
								<v8:item>
									<v8:lang>ru</v8:lang>
									<v8:content>Err</v8:content>
								</v8:item>
							</Synonym>
							<Comment/>
							<XDTOValueType>xs:string</XDTOValueType>
							<Nillable>true</Nillable>
							<TransferDirection>Out</TransferDirection>
						</Properties>
					</Parameter>
				</ChildObjects>
			</Operation>
			<Operation uuid="f1fcfdb4-9f96-4617-b761-f33dc72752cd">
				<Properties>
					<Name>create_delivery_address</Name>
					<Synonym>
						<v8:item>
							<v8:lang>ru</v8:lang>
							<v8:content>Create delivery address</v8:content>
						</v8:item>
					</Synonym>
					<Comment/>
					<XDTOReturningValueType>xs:string</XDTOReturningValueType>
					<Nillable>true</Nillable>
					<Transactioned>false</Transactioned>
					<ProcedureName>create_delivery_address</ProcedureName>
					<DataLockControlMode>Managed</DataLockControlMode>
				</Properties>
				<ChildObjects>
					<Parameter uuid="ce16c77f-1fae-4641-bfca-ef32dbe03b21">
						<Properties>
							<Name>delivery_address</Name>
							<Synonym>
								<v8:item>
									<v8:lang>ru</v8:lang>
									<v8:content>Delivery address</v8:content>
								</v8:item>
							</Synonym>
							<Comment/>
							<XDTOValueType>xs:string</XDTOValueType>
							<Nillable>false</Nillable>
							<TransferDirection>In</TransferDirection>
						</Properties>
					</Parameter>
					<Parameter uuid="9c86a922-e176-4361-b24e-ac1d302f66c9">
						<Properties>
							<Name>err</Name>
							<Synonym>
								<v8:item>
									<v8:lang>ru</v8:lang>
									<v8:content>Err</v8:content>
								</v8:item>
							</Synonym>
							<Comment/>
							<XDTOValueType>xs:string</XDTOValueType>
							<Nillable>true</Nillable>
							<TransferDirection>Out</TransferDirection>
						</Properties>
					</Parameter>
				</ChildObjects>
			</Operation>
			<Operation uuid="b8bed4b4-5744-46cc-8204-6e7a67c63c71">
				<Properties>
					<Name>create_file_extend</Name>
					<Synonym>
						<v8:item>
							<v8:lang>ru</v8:lang>
							<v8:content>Create file extend</v8:content>
						</v8:item>
					</Synonym>
					<Comment/>
					<XDTOReturningValueType>xs:string</XDTOReturningValueType>
					<Nillable>false</Nillable>
					<Transactioned>false</Transactioned>
					<ProcedureName>create_file_extend</ProcedureName>
					<DataLockControlMode>Automatic</DataLockControlMode>
				</Properties>
				<ChildObjects>
					<Parameter uuid="01d1ddb6-b215-4a4c-a212-d916dd438537">
						<Properties>
							<Name>externalfile</Name>
							<Synonym>
								<v8:item>
									<v8:lang>ru</v8:lang>
									<v8:content>externalfile</v8:content>
								</v8:item>
							</Synonym>
							<Comment/>
							<XDTOValueType>xs:string</XDTOValueType>
							<Nillable>false</Nillable>
							<TransferDirection>In</TransferDirection>
						</Properties>
					</Parameter>
					<Parameter uuid="e2298677-cd0b-4443-bd89-52173db915e4">
						<Properties>
							<Name>err</Name>
							<Synonym>
								<v8:item>
									<v8:lang>ru</v8:lang>
									<v8:content>Err</v8:content>
								</v8:item>
							</Synonym>
							<Comment/>
							<XDTOValueType>xs:string</XDTOValueType>
							<Nillable>true</Nillable>
							<TransferDirection>Out</TransferDirection>
						</Properties>
					</Parameter>
				</ChildObjects>
			</Operation>
			<Operation uuid="e98a92e7-eea3-4c3b-8ab2-7ae149d8076a">
				<Properties>
					<Name>create_order</Name>
					<Synonym>
						<v8:item>
							<v8:lang>ru</v8:lang>
							<v8:content>Create order</v8:content>
						</v8:item>
					</Synonym>
					<Comment/>
					<XDTOReturningValueType>xs:string</XDTOReturningValueType>
					<Nillable>true</Nillable>
					<Transactioned>false</Transactioned>
					<ProcedureName>create_order</ProcedureName>
					<DataLockControlMode>Managed</DataLockControlMode>
				</Properties>
				<ChildObjects>
					<Parameter uuid="d7b4f13f-f260-4215-908d-c0dca22a4ba8">
						<Properties>
							<Name>order</Name>
							<Synonym>
								<v8:item>
									<v8:lang>ru</v8:lang>
									<v8:content>Order</v8:content>
								</v8:item>
							</Synonym>
							<Comment/>
							<XDTOValueType>xs:string</XDTOValueType>
							<Nillable>false</Nillable>
							<TransferDirection>In</TransferDirection>
						</Properties>
					</Parameter>
					<Parameter uuid="f97aefcd-d97a-4fd5-be3f-5beb33577cfb">
						<Properties>
							<Name>err</Name>
							<Synonym>
								<v8:item>
									<v8:lang>ru</v8:lang>
									<v8:content>Err</v8:content>
								</v8:item>
							</Synonym>
							<Comment/>
							<XDTOValueType>xs:string</XDTOValueType>
							<Nillable>true</Nillable>
							<TransferDirection>Out</TransferDirection>
						</Properties>
					</Parameter>
				</ChildObjects>
			</Operation>
			<Operation uuid="0bda5371-a8ef-4dcd-949c-5e80eb2c8df4">
				<Properties>
					<Name>create_user</Name>
					<Synonym>
						<v8:item>
							<v8:lang>ru</v8:lang>
							<v8:content>Create user</v8:content>
						</v8:item>
					</Synonym>
					<Comment/>
					<XDTOReturningValueType>xs:string</XDTOReturningValueType>
					<Nillable>true</Nillable>
					<Transactioned>false</Transactioned>
					<ProcedureName>create_user</ProcedureName>
					<DataLockControlMode>Managed</DataLockControlMode>
				</Properties>
				<ChildObjects>
					<Parameter uuid="8c12bae1-a0de-47d6-bf91-26733003272f">
						<Properties>
							<Name>user</Name>
							<Synonym>
								<v8:item>
									<v8:lang>ru</v8:lang>
									<v8:content>User</v8:content>
								</v8:item>
							</Synonym>
							<Comment/>
							<XDTOValueType>xs:string</XDTOValueType>
							<Nillable>false</Nillable>
							<TransferDirection>In</TransferDirection>
						</Properties>
					</Parameter>
					<Parameter uuid="0b44dfb5-36e1-4670-9e91-6f634ac14d12">
						<Properties>
							<Name>err</Name>
							<Synonym>
								<v8:item>
									<v8:lang>ru</v8:lang>
									<v8:content>Err</v8:content>
								</v8:item>
							</Synonym>
							<Comment/>
							<XDTOValueType>xs:string</XDTOValueType>
							<Nillable>true</Nillable>
							<TransferDirection>Out</TransferDirection>
						</Properties>
					</Parameter>
				</ChildObjects>
			</Operation>
			<Operation uuid="0b07d359-0c0f-4d2e-a510-8fb71147105d">
				<Properties>
					<Name>delete_delivery_address</Name>
					<Synonym>
						<v8:item>
							<v8:lang>ru</v8:lang>
							<v8:content>Delete delivery address</v8:content>
						</v8:item>
					</Synonym>
					<Comment/>
					<XDTOReturningValueType>xs:string</XDTOReturningValueType>
					<Nillable>true</Nillable>
					<Transactioned>false</Transactioned>
					<ProcedureName>delete_delivery_address</ProcedureName>
					<DataLockControlMode>Managed</DataLockControlMode>
				</Properties>
				<ChildObjects>
					<Parameter uuid="a6980ce0-e7a4-489f-a1f7-953c66c69067">
						<Properties>
							<Name>delivery_address_guid</Name>
							<Synonym>
								<v8:item>
									<v8:lang>ru</v8:lang>
									<v8:content>Delivery address guid</v8:content>
								</v8:item>
							</Synonym>
							<Comment/>
							<XDTOValueType>xs:string</XDTOValueType>
							<Nillable>false</Nillable>
							<TransferDirection>In</TransferDirection>
						</Properties>
					</Parameter>
					<Parameter uuid="956844d1-3367-4248-b5b9-677c0d24aca8">
						<Properties>
							<Name>err</Name>
							<Synonym>
								<v8:item>
									<v8:lang>ru</v8:lang>
									<v8:content>Err</v8:content>
								</v8:item>
							</Synonym>
							<Comment/>
							<XDTOValueType>xs:string</XDTOValueType>
							<Nillable>true</Nillable>
							<TransferDirection>Out</TransferDirection>
						</Properties>
					</Parameter>
				</ChildObjects>
			</Operation>
			<Operation uuid="b29565c0-feca-4a80-9431-39ff6a8123f5">
				<Properties>
					<Name>delete_order</Name>
					<Synonym>
						<v8:item>
							<v8:lang>ru</v8:lang>
							<v8:content>Delete order</v8:content>
						</v8:item>
					</Synonym>
					<Comment/>
					<XDTOReturningValueType>xs:string</XDTOReturningValueType>
					<Nillable>true</Nillable>
					<Transactioned>false</Transactioned>
					<ProcedureName>delete_order</ProcedureName>
					<DataLockControlMode>Managed</DataLockControlMode>
				</Properties>
				<ChildObjects>
					<Parameter uuid="71caeb06-c7ed-4465-92dd-997a5abf055c">
						<Properties>
							<Name>order</Name>
							<Synonym>
								<v8:item>
									<v8:lang>ru</v8:lang>
									<v8:content>Order</v8:content>
								</v8:item>
							</Synonym>
							<Comment/>
							<XDTOValueType>xs:string</XDTOValueType>
							<Nillable>false</Nillable>
							<TransferDirection>In</TransferDirection>
						</Properties>
					</Parameter>
					<Parameter uuid="3eb09bc9-af51-4a08-b011-b7ed0898d952">
						<Properties>
							<Name>err</Name>
							<Synonym>
								<v8:item>
									<v8:lang>ru</v8:lang>
									<v8:content>Err</v8:content>
								</v8:item>
							</Synonym>
							<Comment/>
							<XDTOValueType>xs:string</XDTOValueType>
							<Nillable>true</Nillable>
							<TransferDirection>Out</TransferDirection>
						</Properties>
					</Parameter>
				</ChildObjects>
			</Operation>
			<Operation uuid="b4d1d01d-200a-46a6-aee4-a40651f47844">
				<Properties>
					<Name>delete_user</Name>
					<Synonym>
						<v8:item>
							<v8:lang>ru</v8:lang>
							<v8:content>Delete user</v8:content>
						</v8:item>
					</Synonym>
					<Comment/>
					<XDTOReturningValueType>xs:string</XDTOReturningValueType>
					<Nillable>true</Nillable>
					<Transactioned>false</Transactioned>
					<ProcedureName>delete_user</ProcedureName>
					<DataLockControlMode>Managed</DataLockControlMode>
				</Properties>
				<ChildObjects>
					<Parameter uuid="df5bff48-9bad-4a67-b288-f86ec592f93f">
						<Properties>
							<Name>user_guid</Name>
							<Synonym>
								<v8:item>
									<v8:lang>ru</v8:lang>
									<v8:content>User guid</v8:content>
								</v8:item>
							</Synonym>
							<Comment/>
							<XDTOValueType>xs:string</XDTOValueType>
							<Nillable>false</Nillable>
							<TransferDirection>In</TransferDirection>
						</Properties>
					</Parameter>
					<Parameter uuid="0e926888-8b1b-4d3b-b74f-14413913251c">
						<Properties>
							<Name>err</Name>
							<Synonym>
								<v8:item>
									<v8:lang>ru</v8:lang>
									<v8:content>Err</v8:content>
								</v8:item>
							</Synonym>
							<Comment/>
							<XDTOValueType>xs:string</XDTOValueType>
							<Nillable>true</Nillable>
							<TransferDirection>Out</TransferDirection>
						</Properties>
					</Parameter>
				</ChildObjects>
			</Operation>
			<Operation uuid="77b3fd42-6e47-4621-b2b5-3be42cb08c56">
				<Properties>
					<Name>get_actions</Name>
					<Synonym>
						<v8:item>
							<v8:lang>ru</v8:lang>
							<v8:content>Get actions</v8:content>
						</v8:item>
					</Synonym>
					<Comment/>
					<XDTOReturningValueType>xs:string</XDTOReturningValueType>
					<Nillable>false</Nillable>
					<Transactioned>false</Transactioned>
					<ProcedureName>get_actions</ProcedureName>
					<DataLockControlMode>Automatic</DataLockControlMode>
				</Properties>
				<ChildObjects>
					<Parameter uuid="2a529c12-dad6-4470-a0c1-f02b724474dc">
						<Properties>
							<Name>guids</Name>
							<Synonym>
								<v8:item>
									<v8:lang>ru</v8:lang>
									<v8:content>Guids</v8:content>
								</v8:item>
							</Synonym>
							<Comment/>
							<XDTOValueType>xs:string</XDTOValueType>
							<Nillable>true</Nillable>
							<TransferDirection>In</TransferDirection>
						</Properties>
					</Parameter>
					<Parameter uuid="ba3fed38-a606-4345-aeae-2e1e0fb494cf">
						<Properties>
							<Name>err</Name>
							<Synonym>
								<v8:item>
									<v8:lang>ru</v8:lang>
									<v8:content>Err</v8:content>
								</v8:item>
							</Synonym>
							<Comment/>
							<XDTOValueType>xs:string</XDTOValueType>
							<Nillable>true</Nillable>
							<TransferDirection>Out</TransferDirection>
						</Properties>
					</Parameter>
				</ChildObjects>
			</Operation>
			<Operation uuid="2a6c8aed-b0ff-4327-8556-429cb13474e0">
				<Properties>
					<Name>get_article_categories</Name>
					<Synonym>
						<v8:item>
							<v8:lang>ru</v8:lang>
							<v8:content>Get article categories</v8:content>
						</v8:item>
					</Synonym>
					<Comment/>
					<XDTOReturningValueType>xs:string</XDTOReturningValueType>
					<Nillable>false</Nillable>
					<Transactioned>false</Transactioned>
					<ProcedureName>get_article_categories</ProcedureName>
					<DataLockControlMode>Automatic</DataLockControlMode>
				</Properties>
				<ChildObjects>
					<Parameter uuid="a25e8c7d-501f-4377-81aa-1847e02d2581">
						<Properties>
							<Name>guids</Name>
							<Synonym>
								<v8:item>
									<v8:lang>ru</v8:lang>
									<v8:content>Guids</v8:content>
								</v8:item>
							</Synonym>
							<Comment/>
							<XDTOValueType>xs:string</XDTOValueType>
							<Nillable>true</Nillable>
							<TransferDirection>In</TransferDirection>
						</Properties>
					</Parameter>
					<Parameter uuid="1e165e74-676b-486b-bbf9-5077d2e45946">
						<Properties>
							<Name>err</Name>
							<Synonym>
								<v8:item>
									<v8:lang>ru</v8:lang>
									<v8:content>Err</v8:content>
								</v8:item>
							</Synonym>
							<Comment/>
							<XDTOValueType>xs:string</XDTOValueType>
							<Nillable>true</Nillable>
							<TransferDirection>Out</TransferDirection>
						</Properties>
					</Parameter>
				</ChildObjects>
			</Operation>
			<Operation uuid="82bde323-154a-430d-9918-ec8a28952f7f">
				<Properties>
					<Name>get_articles</Name>
					<Synonym>
						<v8:item>
							<v8:lang>ru</v8:lang>
							<v8:content>Get articles</v8:content>
						</v8:item>
					</Synonym>
					<Comment/>
					<XDTOReturningValueType>xs:string</XDTOReturningValueType>
					<Nillable>false</Nillable>
					<Transactioned>false</Transactioned>
					<ProcedureName>get_articles</ProcedureName>
					<DataLockControlMode>Automatic</DataLockControlMode>
				</Properties>
				<ChildObjects>
					<Parameter uuid="b1813448-3677-49b8-be08-2f06998bfb41">
						<Properties>
							<Name>guids</Name>
							<Synonym>
								<v8:item>
									<v8:lang>ru</v8:lang>
									<v8:content>Guids</v8:content>
								</v8:item>
							</Synonym>
							<Comment/>
							<XDTOValueType>xs:string</XDTOValueType>
							<Nillable>true</Nillable>
							<TransferDirection>In</TransferDirection>
						</Properties>
					</Parameter>
					<Parameter uuid="ecea0608-d9d5-4446-9690-aa26e1eb58bb">
						<Properties>
							<Name>err</Name>
							<Synonym>
								<v8:item>
									<v8:lang>ru</v8:lang>
									<v8:content>Err</v8:content>
								</v8:item>
							</Synonym>
							<Comment/>
							<XDTOValueType>xs:string</XDTOValueType>
							<Nillable>true</Nillable>
							<TransferDirection>Out</TransferDirection>
						</Properties>
					</Parameter>
				</ChildObjects>
			</Operation>
			<Operation uuid="5b942204-82ba-4d06-84ac-83244405224a">
				<Properties>
					<Name>get_categories</Name>
					<Synonym>
						<v8:item>
							<v8:lang>ru</v8:lang>
							<v8:content>Get categories</v8:content>
						</v8:item>
					</Synonym>
					<Comment/>
					<XDTOReturningValueType>xs:string</XDTOReturningValueType>
					<Nillable>false</Nillable>
					<Transactioned>false</Transactioned>
					<ProcedureName>get_categories</ProcedureName>
					<DataLockControlMode>Automatic</DataLockControlMode>
				</Properties>
				<ChildObjects>
					<Parameter uuid="3deca3c5-352e-4838-a86c-f799aaebbe65">
						<Properties>
							<Name>guids</Name>
							<Synonym>
								<v8:item>
									<v8:lang>ru</v8:lang>
									<v8:content>Guids</v8:content>
								</v8:item>
							</Synonym>
							<Comment/>
							<XDTOValueType>xs:string</XDTOValueType>
							<Nillable>true</Nillable>
							<TransferDirection>In</TransferDirection>
						</Properties>
					</Parameter>
					<Parameter uuid="19b2d5b6-6a7d-45ef-b811-fb4d7ce7ff61">
						<Properties>
							<Name>err</Name>
							<Synonym>
								<v8:item>
									<v8:lang>ru</v8:lang>
									<v8:content>Err</v8:content>
								</v8:item>
							</Synonym>
							<Comment/>
							<XDTOValueType>xs:string</XDTOValueType>
							<Nillable>true</Nillable>
							<TransferDirection>Out</TransferDirection>
						</Properties>
					</Parameter>
				</ChildObjects>
			</Operation>
			<Operation uuid="fadfbefe-ecb5-46b7-bbb2-42d8d148775f">
				<Properties>
					<Name>get_delivery_address</Name>
					<Synonym>
						<v8:item>
							<v8:lang>ru</v8:lang>
							<v8:content>Get delivery address</v8:content>
						</v8:item>
					</Synonym>
					<Comment/>
					<XDTOReturningValueType>xs:string</XDTOReturningValueType>
					<Nillable>false</Nillable>
					<Transactioned>false</Transactioned>
					<ProcedureName>get_delivery_address</ProcedureName>
					<DataLockControlMode>Automatic</DataLockControlMode>
				</Properties>
				<ChildObjects>
					<Parameter uuid="ecb67617-5b31-46a3-9ad4-ec9e842a9441">
						<Properties>
							<Name>guids</Name>
							<Synonym>
								<v8:item>
									<v8:lang>ru</v8:lang>
									<v8:content>Guids</v8:content>
								</v8:item>
							</Synonym>
							<Comment/>
							<XDTOValueType>xs:string</XDTOValueType>
							<Nillable>true</Nillable>
							<TransferDirection>In</TransferDirection>
						</Properties>
					</Parameter>
					<Parameter uuid="041961bf-400e-4b61-97ed-d3a9f41f118f">
						<Properties>
							<Name>err</Name>
							<Synonym>
								<v8:item>
									<v8:lang>ru</v8:lang>
									<v8:content>Err</v8:content>
								</v8:item>
							</Synonym>
							<Comment/>
							<XDTOValueType>xs:string</XDTOValueType>
							<Nillable>true</Nillable>
							<TransferDirection>Out</TransferDirection>
						</Properties>
					</Parameter>
				</ChildObjects>
			</Operation>
			<Operation uuid="f1a108e4-1209-42d6-a957-b4cf807b6c6c">
				<Properties>
					<Name>get_discount_card</Name>
					<Synonym>
						<v8:item>
							<v8:lang>ru</v8:lang>
							<v8:content>Get discount card</v8:content>
						</v8:item>
					</Synonym>
					<Comment/>
					<XDTOReturningValueType>xs:string</XDTOReturningValueType>
					<Nillable>true</Nillable>
					<Transactioned>false</Transactioned>
					<ProcedureName>get_discount_card</ProcedureName>
					<DataLockControlMode>Automatic</DataLockControlMode>
				</Properties>
				<ChildObjects>
					<Parameter uuid="3a648fa0-cf45-498a-b9b8-b09dc1f6c1d3">
						<Properties>
							<Name>discount_card_number</Name>
							<Synonym>
								<v8:item>
									<v8:lang>ru</v8:lang>
									<v8:content>Discount card number</v8:content>
								</v8:item>
							</Synonym>
							<Comment/>
							<XDTOValueType>xs:string</XDTOValueType>
							<Nillable>false</Nillable>
							<TransferDirection>In</TransferDirection>
						</Properties>
					</Parameter>
					<Parameter uuid="40b5690e-3acf-4a6b-b634-460dfaaf8bb5">
						<Properties>
							<Name>err</Name>
							<Synonym>
								<v8:item>
									<v8:lang>ru</v8:lang>
									<v8:content>Err</v8:content>
								</v8:item>
							</Synonym>
							<Comment/>
							<XDTOValueType>xs:string</XDTOValueType>
							<Nillable>true</Nillable>
							<TransferDirection>Out</TransferDirection>
						</Properties>
					</Parameter>
				</ChildObjects>
			</Operation>
			<Operation uuid="830e8455-9d8e-489e-9328-52020768dc92">
				<Properties>
					<Name>get_discount_percents</Name>
					<Synonym>
						<v8:item>
							<v8:lang>ru</v8:lang>
							<v8:content>Get discount percents</v8:content>
						</v8:item>
					</Synonym>
					<Comment/>
					<XDTOReturningValueType>xs:string</XDTOReturningValueType>
					<Nillable>true</Nillable>
					<Transactioned>false</Transactioned>
					<ProcedureName>get_discount_percents</ProcedureName>
					<DataLockControlMode>Automatic</DataLockControlMode>
				</Properties>
				<ChildObjects>
					<Parameter uuid="41c27f73-f542-4306-b5c0-63ed75013a41">
						<Properties>
							<Name>guids</Name>
							<Synonym>
								<v8:item>
									<v8:lang>ru</v8:lang>
									<v8:content>Guids</v8:content>
								</v8:item>
							</Synonym>
							<Comment/>
							<XDTOValueType>xs:string</XDTOValueType>
							<Nillable>true</Nillable>
							<TransferDirection>In</TransferDirection>
						</Properties>
					</Parameter>
					<Parameter uuid="fbbc1c6e-7e15-4583-a575-84db95cb9962">
						<Properties>
							<Name>err</Name>
							<Synonym>
								<v8:item>
									<v8:lang>ru</v8:lang>
									<v8:content>Err</v8:content>
								</v8:item>
							</Synonym>
							<Comment/>
							<XDTOValueType>xs:string</XDTOValueType>
							<Nillable>true</Nillable>
							<TransferDirection>Out</TransferDirection>
						</Properties>
					</Parameter>
				</ChildObjects>
			</Operation>
			<Operation uuid="acf3dbc6-b142-4800-b88c-02566e109006">
				<Properties>
					<Name>get_documents</Name>
					<Synonym>
						<v8:item>
							<v8:lang>ru</v8:lang>
							<v8:content>Get documents</v8:content>
						</v8:item>
					</Synonym>
					<Comment/>
					<XDTOReturningValueType>xs:string</XDTOReturningValueType>
					<Nillable>false</Nillable>
					<Transactioned>false</Transactioned>
					<ProcedureName>get_documents</ProcedureName>
					<DataLockControlMode>Automatic</DataLockControlMode>
				</Properties>
				<ChildObjects>
					<Parameter uuid="1b8f2259-c62b-4243-a824-21ab8c33e262">
						<Properties>
							<Name>guids</Name>
							<Synonym>
								<v8:item>
									<v8:lang>ru</v8:lang>
									<v8:content>Guids</v8:content>
								</v8:item>
							</Synonym>
							<Comment/>
							<XDTOValueType>xs:string</XDTOValueType>
							<Nillable>true</Nillable>
							<TransferDirection>In</TransferDirection>
						</Properties>
					</Parameter>
					<Parameter uuid="94ce6a24-bd0d-4ccc-8faa-078dcb46f2d9">
						<Properties>
							<Name>changesFromDate</Name>
							<Synonym>
								<v8:item>
									<v8:lang>ru</v8:lang>
									<v8:content>Changes from date</v8:content>
								</v8:item>
							</Synonym>
							<Comment/>
							<XDTOValueType>xs:string</XDTOValueType>
							<Nillable>true</Nillable>
							<TransferDirection>In</TransferDirection>
						</Properties>
					</Parameter>
					<Parameter uuid="ee965fa3-769a-467e-a9bf-b2372fb0c58e">
						<Properties>
							<Name>err</Name>
							<Synonym>
								<v8:item>
									<v8:lang>ru</v8:lang>
									<v8:content>Err</v8:content>
								</v8:item>
							</Synonym>
							<Comment/>
							<XDTOValueType>xs:string</XDTOValueType>
							<Nillable>true</Nillable>
							<TransferDirection>Out</TransferDirection>
						</Properties>
					</Parameter>
				</ChildObjects>
			</Operation>
			<Operation uuid="88bfb69f-3681-41da-a827-d733fb861305">
				<Properties>
					<Name>get_external_images</Name>
					<Synonym>
						<v8:item>
							<v8:lang>ru</v8:lang>
							<v8:content>Get external images</v8:content>
						</v8:item>
					</Synonym>
					<Comment/>
					<XDTOReturningValueType>xs:string</XDTOReturningValueType>
					<Nillable>false</Nillable>
					<Transactioned>false</Transactioned>
					<ProcedureName>get_external_images</ProcedureName>
					<DataLockControlMode>Automatic</DataLockControlMode>
				</Properties>
				<ChildObjects>
					<Parameter uuid="71823d23-f264-4273-ab7f-2cae255222e1">
						<Properties>
							<Name>guids</Name>
							<Synonym>
								<v8:item>
									<v8:lang>ru</v8:lang>
									<v8:content>Guids</v8:content>
								</v8:item>
							</Synonym>
							<Comment/>
							<XDTOValueType>xs:string</XDTOValueType>
							<Nillable>true</Nillable>
							<TransferDirection>In</TransferDirection>
						</Properties>
					</Parameter>
					<Parameter uuid="22ca4351-3cbf-4eb9-8de7-01d6bbe63d90">
						<Properties>
							<Name>changesFromDate</Name>
							<Synonym>
								<v8:item>
									<v8:lang>ru</v8:lang>
									<v8:content>Changes from date</v8:content>
								</v8:item>
							</Synonym>
							<Comment/>
							<XDTOValueType>xs:string</XDTOValueType>
							<Nillable>true</Nillable>
							<TransferDirection>In</TransferDirection>
						</Properties>
					</Parameter>
					<Parameter uuid="f8711261-3310-488c-83bb-f1d79328c238">
						<Properties>
							<Name>err</Name>
							<Synonym>
								<v8:item>
									<v8:lang>ru</v8:lang>
									<v8:content>Err</v8:content>
								</v8:item>
							</Synonym>
							<Comment/>
							<XDTOValueType>xs:string</XDTOValueType>
							<Nillable>true</Nillable>
							<TransferDirection>Out</TransferDirection>
						</Properties>
					</Parameter>
				</ChildObjects>
			</Operation>
			<Operation uuid="36e088ee-256b-4b67-be96-fef11af52876">
				<Properties>
					<Name>get_externalfile</Name>
					<Synonym>
						<v8:item>
							<v8:lang>ru</v8:lang>
							<v8:content>Get externalfile</v8:content>
						</v8:item>
					</Synonym>
					<Comment/>
					<XDTOReturningValueType>xs:string</XDTOReturningValueType>
					<Nillable>false</Nillable>
					<Transactioned>false</Transactioned>
					<ProcedureName>get_externalfile</ProcedureName>
					<DataLockControlMode>Automatic</DataLockControlMode>
				</Properties>
				<ChildObjects>
					<Parameter uuid="03d20083-7600-45b3-9b29-3f4c52b155a9">
						<Properties>
							<Name>guids</Name>
							<Synonym>
								<v8:item>
									<v8:lang>ru</v8:lang>
									<v8:content>Guids</v8:content>
								</v8:item>
							</Synonym>
							<Comment/>
							<XDTOValueType>xs:string</XDTOValueType>
							<Nillable>true</Nillable>
							<TransferDirection>In</TransferDirection>
						</Properties>
					</Parameter>
					<Parameter uuid="1df599ec-c4ee-425f-ae4d-26e2e44210c5">
						<Properties>
							<Name>changesFromDate</Name>
							<Synonym>
								<v8:item>
									<v8:lang>ru</v8:lang>
									<v8:content>Changes from date</v8:content>
								</v8:item>
							</Synonym>
							<Comment/>
							<XDTOValueType>xs:string</XDTOValueType>
							<Nillable>true</Nillable>
							<TransferDirection>In</TransferDirection>
						</Properties>
					</Parameter>
					<Parameter uuid="eeae199a-ebe2-4bb4-8291-8ea75f80b03a">
						<Properties>
							<Name>err</Name>
							<Synonym>
								<v8:item>
									<v8:lang>ru</v8:lang>
									<v8:content>Err</v8:content>
								</v8:item>
							</Synonym>
							<Comment/>
							<XDTOValueType>xs:string</XDTOValueType>
							<Nillable>true</Nillable>
							<TransferDirection>Out</TransferDirection>
						</Properties>
					</Parameter>
				</ChildObjects>
			</Operation>
			<Operation uuid="ff56a1b9-da3a-40b9-afa3-598adcf1a307">
				<Properties>
					<Name>get_images</Name>
					<Synonym>
						<v8:item>
							<v8:lang>ru</v8:lang>
							<v8:content>Get images</v8:content>
						</v8:item>
					</Synonym>
					<Comment/>
					<XDTOReturningValueType>xs:string</XDTOReturningValueType>
					<Nillable>false</Nillable>
					<Transactioned>false</Transactioned>
					<ProcedureName>get_images</ProcedureName>
					<DataLockControlMode>Automatic</DataLockControlMode>
				</Properties>
				<ChildObjects>
					<Parameter uuid="6209d25f-1a4e-43ba-ac25-dcaa6797ac05">
						<Properties>
							<Name>guids</Name>
							<Synonym>
								<v8:item>
									<v8:lang>ru</v8:lang>
									<v8:content>Guids</v8:content>
								</v8:item>
							</Synonym>
							<Comment/>
							<XDTOValueType>xs:string</XDTOValueType>
							<Nillable>true</Nillable>
							<TransferDirection>In</TransferDirection>
						</Properties>
					</Parameter>
					<Parameter uuid="5327d3d7-f50a-40c2-abdd-2ea0162f0537">
						<Properties>
							<Name>err</Name>
							<Synonym>
								<v8:item>
									<v8:lang>ru</v8:lang>
									<v8:content>Err</v8:content>
								</v8:item>
							</Synonym>
							<Comment/>
							<XDTOValueType>xs:string</XDTOValueType>
							<Nillable>true</Nillable>
							<TransferDirection>Out</TransferDirection>
						</Properties>
					</Parameter>
				</ChildObjects>
			</Operation>
			<Operation uuid="df3f5414-e458-4faa-bec7-ef7d66bf413d">
				<Properties>
					<Name>get_levels</Name>
					<Synonym>
						<v8:item>
							<v8:lang>ru</v8:lang>
							<v8:content>Get levels</v8:content>
						</v8:item>
					</Synonym>
					<Comment/>
					<XDTOReturningValueType>xs:string</XDTOReturningValueType>
					<Nillable>false</Nillable>
					<Transactioned>false</Transactioned>
					<ProcedureName>get_levels</ProcedureName>
					<DataLockControlMode>Automatic</DataLockControlMode>
				</Properties>
				<ChildObjects>
					<Parameter uuid="b3705e09-8a7f-425d-9867-86bcf527d91e">
						<Properties>
							<Name>users</Name>
							<Synonym>
								<v8:item>
									<v8:lang>ru</v8:lang>
									<v8:content>Users</v8:content>
								</v8:item>
							</Synonym>
							<Comment/>
							<XDTOValueType>xs:string</XDTOValueType>
							<Nillable>false</Nillable>
							<TransferDirection>In</TransferDirection>
						</Properties>
					</Parameter>
					<Parameter uuid="1c8023c8-b90a-41c3-9f44-ba149d9ab80c">
						<Properties>
							<Name>err</Name>
							<Synonym>
								<v8:item>
									<v8:lang>ru</v8:lang>
									<v8:content>Err</v8:content>
								</v8:item>
							</Synonym>
							<Comment/>
							<XDTOValueType>xs:string</XDTOValueType>
							<Nillable>true</Nillable>
							<TransferDirection>Out</TransferDirection>
						</Properties>
					</Parameter>
				</ChildObjects>
			</Operation>
			<Operation uuid="6311450e-4159-4ea2-8ee2-0b1d28f8214c">
				<Properties>
					<Name>get_manufacturers</Name>
					<Synonym>
						<v8:item>
							<v8:lang>ru</v8:lang>
							<v8:content>Get manufacturers</v8:content>
						</v8:item>
					</Synonym>
					<Comment/>
					<XDTOReturningValueType>xs:string</XDTOReturningValueType>
					<Nillable>false</Nillable>
					<Transactioned>false</Transactioned>
					<ProcedureName>get_manufacturers</ProcedureName>
					<DataLockControlMode>Automatic</DataLockControlMode>
				</Properties>
				<ChildObjects>
					<Parameter uuid="41318f50-3784-4bc1-a3a5-69a4f666c554">
						<Properties>
							<Name>guids</Name>
							<Synonym>
								<v8:item>
									<v8:lang>ru</v8:lang>
									<v8:content>Guids</v8:content>
								</v8:item>
							</Synonym>
							<Comment/>
							<XDTOValueType>xs:string</XDTOValueType>
							<Nillable>true</Nillable>
							<TransferDirection>In</TransferDirection>
						</Properties>
					</Parameter>
					<Parameter uuid="8a101187-7f4f-4884-a637-aa2f52343f10">
						<Properties>
							<Name>err</Name>
							<Synonym>
								<v8:item>
									<v8:lang>ru</v8:lang>
									<v8:content>Err</v8:content>
								</v8:item>
							</Synonym>
							<Comment/>
							<XDTOValueType>xs:string</XDTOValueType>
							<Nillable>true</Nillable>
							<TransferDirection>Out</TransferDirection>
						</Properties>
					</Parameter>
				</ChildObjects>
			</Operation>
			<Operation uuid="aaf17220-aca9-4279-85c8-9d99c5887a7a">
				<Properties>
					<Name>get_orders</Name>
					<Synonym>
						<v8:item>
							<v8:lang>ru</v8:lang>
							<v8:content>Get orders</v8:content>
						</v8:item>
					</Synonym>
					<Comment/>
					<XDTOReturningValueType>xs:string</XDTOReturningValueType>
					<Nillable>false</Nillable>
					<Transactioned>false</Transactioned>
					<ProcedureName>get_orders</ProcedureName>
					<DataLockControlMode>Automatic</DataLockControlMode>
				</Properties>
				<ChildObjects>
					<Parameter uuid="46b6d685-fe3b-4b35-a48b-ac34498cf949">
						<Properties>
							<Name>guids</Name>
							<Synonym>
								<v8:item>
									<v8:lang>ru</v8:lang>
									<v8:content>Guids</v8:content>
								</v8:item>
							</Synonym>
							<Comment/>
							<XDTOValueType>xs:string</XDTOValueType>
							<Nillable>true</Nillable>
							<TransferDirection>In</TransferDirection>
						</Properties>
					</Parameter>
					<Parameter uuid="9010002b-4ffd-4a3b-976f-018dc4fba8af">
						<Properties>
							<Name>err</Name>
							<Synonym>
								<v8:item>
									<v8:lang>ru</v8:lang>
									<v8:content>Err</v8:content>
								</v8:item>
							</Synonym>
							<Comment/>
							<XDTOValueType>xs:string</XDTOValueType>
							<Nillable>true</Nillable>
							<TransferDirection>Out</TransferDirection>
						</Properties>
					</Parameter>
				</ChildObjects>
			</Operation>
			<Operation uuid="2c58493a-0e3d-46ff-9fbf-65a98a21b08a">
				<Properties>
					<Name>get_payment_variants</Name>
					<Synonym>
						<v8:item>
							<v8:lang>ru</v8:lang>
							<v8:content>Get payment variants</v8:content>
						</v8:item>
					</Synonym>
					<Comment/>
					<XDTOReturningValueType>xs:string</XDTOReturningValueType>
					<Nillable>false</Nillable>
					<Transactioned>false</Transactioned>
					<ProcedureName>get_payment_variants</ProcedureName>
					<DataLockControlMode>Automatic</DataLockControlMode>
				</Properties>
				<ChildObjects>
					<Parameter uuid="03b51f28-290c-4c39-afd7-26472da9fd91">
						<Properties>
							<Name>guids</Name>
							<Synonym>
								<v8:item>
									<v8:lang>ru</v8:lang>
									<v8:content>Guids</v8:content>
								</v8:item>
							</Synonym>
							<Comment/>
							<XDTOValueType>xs:string</XDTOValueType>
							<Nillable>true</Nillable>
							<TransferDirection>In</TransferDirection>
						</Properties>
					</Parameter>
					<Parameter uuid="21d06a6a-c585-4dc7-9591-ca4c554f170e">
						<Properties>
							<Name>err</Name>
							<Synonym>
								<v8:item>
									<v8:lang>ru</v8:lang>
									<v8:content>Err</v8:content>
								</v8:item>
							</Synonym>
							<Comment/>
							<XDTOValueType>xs:string</XDTOValueType>
							<Nillable>true</Nillable>
							<TransferDirection>Out</TransferDirection>
						</Properties>
					</Parameter>
				</ChildObjects>
			</Operation>
			<Operation uuid="ddb2181b-12d5-4002-a6fb-ee2ff5703527">
				<Properties>
					<Name>get_products</Name>
					<Synonym>
						<v8:item>
							<v8:lang>ru</v8:lang>
							<v8:content>Get products</v8:content>
						</v8:item>
					</Synonym>
					<Comment/>
					<XDTOReturningValueType>xs:string</XDTOReturningValueType>
					<Nillable>false</Nillable>
					<Transactioned>false</Transactioned>
					<ProcedureName>get_products</ProcedureName>
					<DataLockControlMode>Automatic</DataLockControlMode>
				</Properties>
				<ChildObjects>
					<Parameter uuid="6f479006-b8b3-48de-84fe-da84d8a175c2">
						<Properties>
							<Name>guid_category</Name>
							<Synonym>
								<v8:item>
									<v8:lang>ru</v8:lang>
									<v8:content>Guid category</v8:content>
								</v8:item>
							</Synonym>
							<Comment/>
							<XDTOValueType>xs:string</XDTOValueType>
							<Nillable>true</Nillable>
							<TransferDirection>In</TransferDirection>
						</Properties>
					</Parameter>
					<Parameter uuid="e14f8407-ba7d-4556-9efd-4dc924715d09">
						<Properties>
							<Name>guids</Name>
							<Synonym>
								<v8:item>
									<v8:lang>ru</v8:lang>
									<v8:content>Guids</v8:content>
								</v8:item>
							</Synonym>
							<Comment/>
							<XDTOValueType>xs:string</XDTOValueType>
							<Nillable>true</Nillable>
							<TransferDirection>In</TransferDirection>
						</Properties>
					</Parameter>
					<Parameter uuid="2f3cdcbc-6937-4301-b73e-f4a5d03e6f1f">
						<Properties>
							<Name>begin_number</Name>
							<Synonym>
								<v8:item>
									<v8:lang>ru</v8:lang>
									<v8:content>Begin number</v8:content>
								</v8:item>
							</Synonym>
							<Comment/>
							<XDTOValueType>xs:int</XDTOValueType>
							<Nillable>true</Nillable>
							<TransferDirection>In</TransferDirection>
						</Properties>
					</Parameter>
					<Parameter uuid="fb4cdc0d-5baf-4456-a3fa-81a51b11f5e3">
						<Properties>
							<Name>end_number</Name>
							<Synonym>
								<v8:item>
									<v8:lang>ru</v8:lang>
									<v8:content>End number</v8:content>
								</v8:item>
							</Synonym>
							<Comment/>
							<XDTOValueType>xs:int</XDTOValueType>
							<Nillable>true</Nillable>
							<TransferDirection>In</TransferDirection>
						</Properties>
					</Parameter>
					<Parameter uuid="4a4bd1fd-ec1d-42b3-8d98-cc70d792f10e">
						<Properties>
							<Name>err</Name>
							<Synonym>
								<v8:item>
									<v8:lang>ru</v8:lang>
									<v8:content>Err</v8:content>
								</v8:item>
							</Synonym>
							<Comment/>
							<XDTOValueType>xs:string</XDTOValueType>
							<Nillable>true</Nillable>
							<TransferDirection>Out</TransferDirection>
						</Properties>
					</Parameter>
				</ChildObjects>
			</Operation>
			<Operation uuid="03e66ec6-c508-47bb-9cc7-4ec642854eef">
				<Properties>
					<Name>get_products_count</Name>
					<Synonym>
						<v8:item>
							<v8:lang>ru</v8:lang>
							<v8:content>Get products count</v8:content>
						</v8:item>
					</Synonym>
					<Comment/>
					<XDTOReturningValueType>xs:string</XDTOReturningValueType>
					<Nillable>false</Nillable>
					<Transactioned>false</Transactioned>
					<ProcedureName>get_products_count</ProcedureName>
					<DataLockControlMode>Managed</DataLockControlMode>
				</Properties>
				<ChildObjects>
					<Parameter uuid="6d598c46-b86a-47fc-be5b-d9d517196552">
						<Properties>
							<Name>guid_category</Name>
							<Synonym>
								<v8:item>
									<v8:lang>ru</v8:lang>
									<v8:content>Guid category</v8:content>
								</v8:item>
							</Synonym>
							<Comment/>
							<XDTOValueType>xs:string</XDTOValueType>
							<Nillable>true</Nillable>
							<TransferDirection>In</TransferDirection>
						</Properties>
					</Parameter>
					<Parameter uuid="decc3d8a-23ed-4388-bfc5-0bf8cf45e5a0">
						<Properties>
							<Name>err</Name>
							<Synonym>
								<v8:item>
									<v8:lang>ru</v8:lang>
									<v8:content>Err</v8:content>
								</v8:item>
							</Synonym>
							<Comment/>
							<XDTOValueType>xs:string</XDTOValueType>
							<Nillable>true</Nillable>
							<TransferDirection>Out</TransferDirection>
						</Properties>
					</Parameter>
				</ChildObjects>
			</Operation>
			<Operation uuid="717f88e7-8b74-4f46-8c9b-37116acdd78c">
				<Properties>
					<Name>get_products_list</Name>
					<Synonym>
						<v8:item>
							<v8:lang>ru</v8:lang>
							<v8:content>Get products list</v8:content>
						</v8:item>
					</Synonym>
					<Comment/>
					<XDTOReturningValueType>xs:string</XDTOReturningValueType>
					<Nillable>false</Nillable>
					<Transactioned>false</Transactioned>
					<ProcedureName>get_products_list</ProcedureName>
					<DataLockControlMode>Automatic</DataLockControlMode>
				</Properties>
				<ChildObjects>
					<Parameter uuid="4d732689-778f-4c46-82ad-6e4c980a4b00">
						<Properties>
							<Name>list_name</Name>
							<Synonym>
								<v8:item>
									<v8:lang>ru</v8:lang>
									<v8:content>List name</v8:content>
								</v8:item>
							</Synonym>
							<Comment/>
							<XDTOValueType>xs:string</XDTOValueType>
							<Nillable>true</Nillable>
							<TransferDirection>In</TransferDirection>
						</Properties>
					</Parameter>
					<Parameter uuid="96b467b3-86cb-4377-8e76-74dea6e2cfe6">
						<Properties>
							<Name>err</Name>
							<Synonym>
								<v8:item>
									<v8:lang>ru</v8:lang>
									<v8:content>Err</v8:content>
								</v8:item>
							</Synonym>
							<Comment/>
							<XDTOValueType>xs:string</XDTOValueType>
							<Nillable>true</Nillable>
							<TransferDirection>Out</TransferDirection>
						</Properties>
					</Parameter>
				</ChildObjects>
			</Operation>
			<Operation uuid="d8c8a757-8573-41e3-a7c4-8adef54265b5">
				<Properties>
					<Name>get_properties</Name>
					<Synonym>
						<v8:item>
							<v8:lang>ru</v8:lang>
							<v8:content>Get properties</v8:content>
						</v8:item>
					</Synonym>
					<Comment/>
					<XDTOReturningValueType>xs:string</XDTOReturningValueType>
					<Nillable>false</Nillable>
					<Transactioned>false</Transactioned>
					<ProcedureName>get_properties</ProcedureName>
					<DataLockControlMode>Automatic</DataLockControlMode>
				</Properties>
				<ChildObjects>
					<Parameter uuid="70a95002-67b9-499f-bc65-b702af868fe5">
						<Properties>
							<Name>guids</Name>
							<Synonym>
								<v8:item>
									<v8:lang>ru</v8:lang>
									<v8:content>Guids</v8:content>
								</v8:item>
							</Synonym>
							<Comment/>
							<XDTOValueType>xs:string</XDTOValueType>
							<Nillable>true</Nillable>
							<TransferDirection>In</TransferDirection>
						</Properties>
					</Parameter>
					<Parameter uuid="a2ae5df1-f2a9-403a-b9de-902d23dc2e51">
						<Properties>
							<Name>err</Name>
							<Synonym>
								<v8:item>
									<v8:lang>ru</v8:lang>
									<v8:content>Err</v8:content>
								</v8:item>
							</Synonym>
							<Comment/>
							<XDTOValueType>xs:string</XDTOValueType>
							<Nillable>true</Nillable>
							<TransferDirection>Out</TransferDirection>
						</Properties>
					</Parameter>
				</ChildObjects>
			</Operation>
			<Operation uuid="6ede2a46-c6b2-43c1-be59-801f90cb06a1">
				<Properties>
					<Name>get_severstal_limits</Name>
					<Synonym>
						<v8:item>
							<v8:lang>ru</v8:lang>
							<v8:content>Get severstal limits</v8:content>
						</v8:item>
					</Synonym>
					<Comment/>
					<XDTOReturningValueType>xs:string</XDTOReturningValueType>
					<Nillable>false</Nillable>
					<Transactioned>false</Transactioned>
					<ProcedureName>get_severstal_limits</ProcedureName>
					<DataLockControlMode>Automatic</DataLockControlMode>
				</Properties>
				<ChildObjects>
					<Parameter uuid="c1ce1c9f-ecb0-4b54-8a89-eb7ee2932373">
						<Properties>
							<Name>guids</Name>
							<Synonym>
								<v8:item>
									<v8:lang>ru</v8:lang>
									<v8:content>Guids</v8:content>
								</v8:item>
							</Synonym>
							<Comment/>
							<XDTOValueType>xs:string</XDTOValueType>
							<Nillable>true</Nillable>
							<TransferDirection>In</TransferDirection>
						</Properties>
					</Parameter>
					<Parameter uuid="93e54a19-ecc2-48ac-b16e-40d2710e2e51">
						<Properties>
							<Name>err</Name>
							<Synonym>
								<v8:item>
									<v8:lang>ru</v8:lang>
									<v8:content>Err</v8:content>
								</v8:item>
							</Synonym>
							<Comment/>
							<XDTOValueType>xs:string</XDTOValueType>
							<Nillable>true</Nillable>
							<TransferDirection>Out</TransferDirection>
						</Properties>
					</Parameter>
				</ChildObjects>
			</Operation>
			<Operation uuid="0b8fde17-42e9-46fd-9427-330589012442">
				<Properties>
					<Name>get_type_prices</Name>
					<Synonym>
						<v8:item>
							<v8:lang>ru</v8:lang>
							<v8:content>Get type prices</v8:content>
						</v8:item>
					</Synonym>
					<Comment/>
					<XDTOReturningValueType>xs:string</XDTOReturningValueType>
					<Nillable>false</Nillable>
					<Transactioned>false</Transactioned>
					<ProcedureName>get_type_prices</ProcedureName>
					<DataLockControlMode>Automatic</DataLockControlMode>
				</Properties>
				<ChildObjects>
					<Parameter uuid="08288b7d-5740-4409-b3f9-9e5fcd6bf725">
						<Properties>
							<Name>guids</Name>
							<Synonym>
								<v8:item>
									<v8:lang>ru</v8:lang>
									<v8:content>Guids</v8:content>
								</v8:item>
							</Synonym>
							<Comment/>
							<XDTOValueType>xs:string</XDTOValueType>
							<Nillable>true</Nillable>
							<TransferDirection>In</TransferDirection>
						</Properties>
					</Parameter>
					<Parameter uuid="b9b41990-014f-4a27-937b-b0e489e6af82">
						<Properties>
							<Name>err</Name>
							<Synonym>
								<v8:item>
									<v8:lang>ru</v8:lang>
									<v8:content>Err</v8:content>
								</v8:item>
							</Synonym>
							<Comment/>
							<XDTOValueType>xs:string</XDTOValueType>
							<Nillable>true</Nillable>
							<TransferDirection>Out</TransferDirection>
						</Properties>
					</Parameter>
				</ChildObjects>
			</Operation>
			<Operation uuid="1fac457e-a7c7-4ebd-b322-ef82caa11bae">
				<Properties>
					<Name>get_users</Name>
					<Synonym>
						<v8:item>
							<v8:lang>ru</v8:lang>
							<v8:content>Get users</v8:content>
						</v8:item>
					</Synonym>
					<Comment/>
					<XDTOReturningValueType>xs:string</XDTOReturningValueType>
					<Nillable>false</Nillable>
					<Transactioned>false</Transactioned>
					<ProcedureName>get_users</ProcedureName>
					<DataLockControlMode>Automatic</DataLockControlMode>
				</Properties>
				<ChildObjects>
					<Parameter uuid="f7c4c744-ebd6-45c9-bec7-a4704777bb84">
						<Properties>
							<Name>guids</Name>
							<Synonym>
								<v8:item>
									<v8:lang>ru</v8:lang>
									<v8:content>Guids</v8:content>
								</v8:item>
							</Synonym>
							<Comment/>
							<XDTOValueType>xs:string</XDTOValueType>
							<Nillable>true</Nillable>
							<TransferDirection>In</TransferDirection>
						</Properties>
					</Parameter>
					<Parameter uuid="3db60c42-6529-4ada-a6e0-f60dd0d4f5ea">
						<Properties>
							<Name>err</Name>
							<Synonym>
								<v8:item>
									<v8:lang>ru</v8:lang>
									<v8:content>Err</v8:content>
								</v8:item>
							</Synonym>
							<Comment/>
							<XDTOValueType>xs:string</XDTOValueType>
							<Nillable>true</Nillable>
							<TransferDirection>Out</TransferDirection>
						</Properties>
					</Parameter>
				</ChildObjects>
			</Operation>
			<Operation uuid="b9b016c1-fe4a-433f-89ea-d5f15c061e6b">
				<Properties>
					<Name>get_warehouses</Name>
					<Synonym>
						<v8:item>
							<v8:lang>ru</v8:lang>
							<v8:content>Get warehouses</v8:content>
						</v8:item>
					</Synonym>
					<Comment/>
					<XDTOReturningValueType>xs:string</XDTOReturningValueType>
					<Nillable>false</Nillable>
					<Transactioned>false</Transactioned>
					<ProcedureName>get_warehouses</ProcedureName>
					<DataLockControlMode>Automatic</DataLockControlMode>
				</Properties>
				<ChildObjects>
					<Parameter uuid="ec95cbc4-17ee-4888-a6d7-a970b7cbd975">
						<Properties>
							<Name>guids</Name>
							<Synonym>
								<v8:item>
									<v8:lang>ru</v8:lang>
									<v8:content>Guids</v8:content>
								</v8:item>
							</Synonym>
							<Comment/>
							<XDTOValueType>xs:string</XDTOValueType>
							<Nillable>true</Nillable>
							<TransferDirection>In</TransferDirection>
						</Properties>
					</Parameter>
					<Parameter uuid="d40ccd7d-d392-4902-8e51-521dd73e9b1a">
						<Properties>
							<Name>err</Name>
							<Synonym>
								<v8:item>
									<v8:lang>ru</v8:lang>
									<v8:content>Err</v8:content>
								</v8:item>
							</Synonym>
							<Comment/>
							<XDTOValueType>xs:string</XDTOValueType>
							<Nillable>true</Nillable>
							<TransferDirection>Out</TransferDirection>
						</Properties>
					</Parameter>
				</ChildObjects>
			</Operation>
			<Operation uuid="5aa650ac-986e-4659-a0ab-26840c975ec2">
				<Properties>
					<Name>payment_order</Name>
					<Synonym>
						<v8:item>
							<v8:lang>ru</v8:lang>
							<v8:content>Payment order</v8:content>
						</v8:item>
					</Synonym>
					<Comment/>
					<XDTOReturningValueType>xs:string</XDTOReturningValueType>
					<Nillable>false</Nillable>
					<Transactioned>false</Transactioned>
					<ProcedureName>payment_order</ProcedureName>
					<DataLockControlMode>Automatic</DataLockControlMode>
				</Properties>
				<ChildObjects>
					<Parameter uuid="b8c9238b-4f83-40c9-8a82-0d8d69540a8a">
						<Properties>
							<Name>order</Name>
							<Synonym>
								<v8:item>
									<v8:lang>ru</v8:lang>
									<v8:content>Order</v8:content>
								</v8:item>
							</Synonym>
							<Comment/>
							<XDTOValueType>xs:string</XDTOValueType>
							<Nillable>false</Nillable>
							<TransferDirection>In</TransferDirection>
						</Properties>
					</Parameter>
					<Parameter uuid="5812a0b8-f5c1-432b-ac7f-1ba44a9225f4">
						<Properties>
							<Name>err</Name>
							<Synonym>
								<v8:item>
									<v8:lang>ru</v8:lang>
									<v8:content>Err</v8:content>
								</v8:item>
							</Synonym>
							<Comment/>
							<XDTOValueType>xs:string</XDTOValueType>
							<Nillable>true</Nillable>
							<TransferDirection>Out</TransferDirection>
						</Properties>
					</Parameter>
				</ChildObjects>
			</Operation>
			<Operation uuid="41b8c70b-6711-4814-8390-ecd7d1662b08">
				<Properties>
					<Name>Request1CWebTable</Name>
					<Synonym>
						<v8:item>
							<v8:lang>ru</v8:lang>
							<v8:content>Request1 c web table</v8:content>
						</v8:item>
					</Synonym>
					<Comment/>
					<XDTOReturningValueType>xs:string</XDTOReturningValueType>
					<Nillable>false</Nillable>
					<Transactioned>false</Transactioned>
					<ProcedureName>Request1CWebTable</ProcedureName>
					<DataLockControlMode>Automatic</DataLockControlMode>
				</Properties>
				<ChildObjects>
					<Parameter uuid="6e5e8f97-042f-4309-9e30-827735e8ea80">
						<Properties>
							<Name>Request1C</Name>
							<Synonym>
								<v8:item>
									<v8:lang>ru</v8:lang>
									<v8:content>Request1 C</v8:content>
								</v8:item>
							</Synonym>
							<Comment/>
							<XDTOValueType>xs:string</XDTOValueType>
							<Nillable>false</Nillable>
							<TransferDirection>In</TransferDirection>
						</Properties>
					</Parameter>
					<Parameter uuid="68088960-3e81-45b0-ad39-cc82deb3185b">
						<Properties>
							<Name>ТableData</Name>
							<Synonym>
								<v8:item>
									<v8:lang>ru</v8:lang>
									<v8:content>Тable data</v8:content>
								</v8:item>
							</Synonym>
							<Comment/>
							<XDTOValueType>xs:string</XDTOValueType>
							<Nillable>false</Nillable>
							<TransferDirection>In</TransferDirection>
						</Properties>
					</Parameter>
				</ChildObjects>
			</Operation>
			<Operation uuid="0b01848b-b2cb-4d68-bd19-8359dae7d2f3">
				<Properties>
					<Name>update_delivery_address</Name>
					<Synonym>
						<v8:item>
							<v8:lang>ru</v8:lang>
							<v8:content>Update delivery address</v8:content>
						</v8:item>
					</Synonym>
					<Comment/>
					<XDTOReturningValueType>xs:string</XDTOReturningValueType>
					<Nillable>true</Nillable>
					<Transactioned>false</Transactioned>
					<ProcedureName>update_delivery_address</ProcedureName>
					<DataLockControlMode>Managed</DataLockControlMode>
				</Properties>
				<ChildObjects>
					<Parameter uuid="9fa6550f-6535-4d46-88d9-11a06e5e6f55">
						<Properties>
							<Name>delivery_address</Name>
							<Synonym>
								<v8:item>
									<v8:lang>ru</v8:lang>
									<v8:content>Delivery address</v8:content>
								</v8:item>
							</Synonym>
							<Comment/>
							<XDTOValueType>xs:string</XDTOValueType>
							<Nillable>false</Nillable>
							<TransferDirection>In</TransferDirection>
						</Properties>
					</Parameter>
					<Parameter uuid="8ba56489-a25e-49ef-b176-d7772d317950">
						<Properties>
							<Name>err</Name>
							<Synonym>
								<v8:item>
									<v8:lang>ru</v8:lang>
									<v8:content>Err</v8:content>
								</v8:item>
							</Synonym>
							<Comment/>
							<XDTOValueType>xs:string</XDTOValueType>
							<Nillable>true</Nillable>
							<TransferDirection>Out</TransferDirection>
						</Properties>
					</Parameter>
				</ChildObjects>
			</Operation>
			<Operation uuid="043fc873-4924-4a12-92e0-f09d38199d76">
				<Properties>
					<Name>update_order</Name>
					<Synonym>
						<v8:item>
							<v8:lang>ru</v8:lang>
							<v8:content>Update order</v8:content>
						</v8:item>
					</Synonym>
					<Comment/>
					<XDTOReturningValueType>xs:string</XDTOReturningValueType>
					<Nillable>true</Nillable>
					<Transactioned>false</Transactioned>
					<ProcedureName>update_order</ProcedureName>
					<DataLockControlMode>Managed</DataLockControlMode>
				</Properties>
				<ChildObjects>
					<Parameter uuid="1eb4d518-c44d-45bc-895e-aaabc477f3e4">
						<Properties>
							<Name>order</Name>
							<Synonym>
								<v8:item>
									<v8:lang>ru</v8:lang>
									<v8:content>Order</v8:content>
								</v8:item>
							</Synonym>
							<Comment/>
							<XDTOValueType>xs:string</XDTOValueType>
							<Nillable>false</Nillable>
							<TransferDirection>In</TransferDirection>
						</Properties>
					</Parameter>
					<Parameter uuid="f3e089b9-772a-4b6a-a2cd-9363bff2476c">
						<Properties>
							<Name>err</Name>
							<Synonym>
								<v8:item>
									<v8:lang>ru</v8:lang>
									<v8:content>Err</v8:content>
								</v8:item>
							</Synonym>
							<Comment/>
							<XDTOValueType>xs:string</XDTOValueType>
							<Nillable>true</Nillable>
							<TransferDirection>Out</TransferDirection>
						</Properties>
					</Parameter>
				</ChildObjects>
			</Operation>
			<Operation uuid="2c83deae-8fd8-4015-9c74-0731901ddc48">
				<Properties>
					<Name>update_user</Name>
					<Synonym>
						<v8:item>
							<v8:lang>ru</v8:lang>
							<v8:content>Update user</v8:content>
						</v8:item>
					</Synonym>
					<Comment/>
					<XDTOReturningValueType>xs:string</XDTOReturningValueType>
					<Nillable>true</Nillable>
					<Transactioned>false</Transactioned>
					<ProcedureName>update_user</ProcedureName>
					<DataLockControlMode>Managed</DataLockControlMode>
				</Properties>
				<ChildObjects>
					<Parameter uuid="c6d27323-1378-4689-800d-ff10135d0d5d">
						<Properties>
							<Name>user</Name>
							<Synonym>
								<v8:item>
									<v8:lang>ru</v8:lang>
									<v8:content>User</v8:content>
								</v8:item>
							</Synonym>
							<Comment/>
							<XDTOValueType>xs:string</XDTOValueType>
							<Nillable>false</Nillable>
							<TransferDirection>In</TransferDirection>
						</Properties>
					</Parameter>
					<Parameter uuid="88b796d7-6d6e-49e6-86ab-26f55d8992bd">
						<Properties>
							<Name>err</Name>
							<Synonym>
								<v8:item>
									<v8:lang>ru</v8:lang>
									<v8:content>Err</v8:content>
								</v8:item>
							</Synonym>
							<Comment/>
							<XDTOValueType>xs:string</XDTOValueType>
							<Nillable>true</Nillable>
							<TransferDirection>Out</TransferDirection>
						</Properties>
					</Parameter>
				</ChildObjects>
			</Operation>
			<Operation uuid="03c0fb12-af33-4b26-b12a-1a308e691875">
				<Properties>
					<Name>create_reconcile</Name>
					<Synonym>
						<v8:item>
							<v8:lang>ru</v8:lang>
							<v8:content>Create reconcile</v8:content>
						</v8:item>
					</Synonym>
					<Comment/>
					<XDTOReturningValueType>xs:string</XDTOReturningValueType>
					<Nillable>false</Nillable>
					<Transactioned>false</Transactioned>
					<ProcedureName>create_reconcile</ProcedureName>
					<DataLockControlMode>Automatic</DataLockControlMode>
				</Properties>
				<ChildObjects>
					<Parameter uuid="48db7450-ea87-4e28-84c1-de7e189791f9">
						<Properties>
							<Name>reconcile</Name>
							<Synonym>
								<v8:item>
									<v8:lang>ru</v8:lang>
									<v8:content>Reconcile</v8:content>
								</v8:item>
							</Synonym>
							<Comment/>
							<XDTOValueType>xs:string</XDTOValueType>
							<Nillable>false</Nillable>
							<TransferDirection>In</TransferDirection>
						</Properties>
					</Parameter>
					<Parameter uuid="9c0608ba-64b1-4d38-b6c1-46ccd149a274">
						<Properties>
							<Name>err</Name>
							<Synonym>
								<v8:item>
									<v8:lang>ru</v8:lang>
									<v8:content>Err</v8:content>
								</v8:item>
							</Synonym>
							<Comment/>
							<XDTOValueType>xs:string</XDTOValueType>
							<Nillable>true</Nillable>
							<TransferDirection>Out</TransferDirection>
						</Properties>
					</Parameter>
				</ChildObjects>
			</Operation>
			<Operation uuid="208c0bd7-852b-4745-9662-9d0f74f791a4">
				<Properties>
					<Name>get_reconcile</Name>
					<Synonym>
						<v8:item>
							<v8:lang>ru</v8:lang>
							<v8:content>Get reconcile</v8:content>
						</v8:item>
					</Synonym>
					<Comment/>
					<XDTOReturningValueType>xs:string</XDTOReturningValueType>
					<Nillable>false</Nillable>
					<Transactioned>false</Transactioned>
					<ProcedureName>get_reconcile</ProcedureName>
					<DataLockControlMode>Automatic</DataLockControlMode>
				</Properties>
				<ChildObjects>
					<Parameter uuid="9de47f8e-8d2e-4cd1-897f-106a7b0e9b4e">
						<Properties>
							<Name>guids</Name>
							<Synonym>
								<v8:item>
									<v8:lang>ru</v8:lang>
									<v8:content>Guids</v8:content>
								</v8:item>
							</Synonym>
							<Comment/>
							<XDTOValueType>xs:string</XDTOValueType>
							<Nillable>true</Nillable>
							<TransferDirection>In</TransferDirection>
						</Properties>
					</Parameter>
					<Parameter uuid="bf08f13c-b48a-4693-94ce-cb473f8ff001">
						<Properties>
							<Name>err</Name>
							<Synonym>
								<v8:item>
									<v8:lang>ru</v8:lang>
									<v8:content>Err</v8:content>
								</v8:item>
							</Synonym>
							<Comment/>
							<XDTOValueType>xs:string</XDTOValueType>
							<Nillable>true</Nillable>
							<TransferDirection>Out</TransferDirection>
						</Properties>
					</Parameter>
				</ChildObjects>
			</Operation>
			<Operation uuid="db21d13c-59a1-4e24-9ad3-ac4a45caaa44">
				<Properties>
					<Name>get_managers</Name>
					<Synonym>
						<v8:item>
							<v8:lang>ru</v8:lang>
							<v8:content>Get managers</v8:content>
						</v8:item>
					</Synonym>
					<Comment/>
					<XDTOReturningValueType>xs:string</XDTOReturningValueType>
					<Nillable>false</Nillable>
					<Transactioned>false</Transactioned>
					<ProcedureName>get_managers</ProcedureName>
					<DataLockControlMode>Automatic</DataLockControlMode>
				</Properties>
				<ChildObjects>
					<Parameter uuid="9f986b55-42ce-4ab2-98d4-5879e4dc4c41">
						<Properties>
							<Name>guids</Name>
							<Synonym>
								<v8:item>
									<v8:lang>ru</v8:lang>
									<v8:content>Guids</v8:content>
								</v8:item>
							</Synonym>
							<Comment/>
							<XDTOValueType>xs:string</XDTOValueType>
							<Nillable>true</Nillable>
							<TransferDirection>In</TransferDirection>
						</Properties>
					</Parameter>
					<Parameter uuid="488a975c-ac70-4d66-86e4-80ef5a3e54a8">
						<Properties>
							<Name>err</Name>
							<Synonym>
								<v8:item>
									<v8:lang>ru</v8:lang>
									<v8:content>Err</v8:content>
								</v8:item>
							</Synonym>
							<Comment/>
							<XDTOValueType>xs:string</XDTOValueType>
							<Nillable>true</Nillable>
							<TransferDirection>Out</TransferDirection>
						</Properties>
					</Parameter>
				</ChildObjects>
			</Operation>
		</ChildObjects>
	</WebService>
</MetaDataObject>